wavlmmsdd/__init__.py
wavlmmsdd/main.py
wavlmmsdd/audio/__init__.py
wavlmmsdd/audio/diarization/__init__.py
wavlmmsdd/audio/diarization/diarize.py
wavlmmsdd/audio/feature/__init__.py
wavlmmsdd/audio/feature/embedding.py
wavlmmsdd/audio/preprocess/__init__.py
wavlmmsdd/audio/preprocess/convert.py
wavlmmsdd/audio/preprocess/resample.py
wavlmmsdd/audio/utils/__init__.py
wavlmmsdd/audio/utils/utils.py
wavlmmsdd/config/__init__.py
wavlmmsdd/config/config.yaml
wavlmmsdd/config/diar_infer_telephonic.yaml
wavlmmsdd-0.1.9.dist-info/LICENSE
wavlmmsdd-0.1.9.dist-info/METADATA
wavlmmsdd-0.1.9.dist-info/WHEEL
wavlmmsdd-0.1.9.dist-info/entry_points.txt
wavlmmsdd-0.1.9.dist-info/top_level.txt
wavlmmsdd-0.1.9.dist-info/RECORD
