Metadata-Version: 2.2
Name: wavlmmsdd
Version: 0.1.9
Summary: WavLM based diarization with MSDD
Author-email: Bunyamin Ergen <info@bunyaminergen.com>
License:                     GNU GENERAL PUBLIC LICENSE
Project-URL: Source Code, https://github.com/bunyaminergen/wavlmmsdd
Project-URL: Issue Tracker, https://github.com/bunyaminergen/wavlmmsdd/issues
Keywords: speech,diarization,wavlm,msdd
Classifier: Development Status :: 3 - Alpha
Classifier: Programming Language :: Python :: 3.11
Classifier: Programming Language :: Python :: 3.12
Classifier: License :: OSI Approved :: GNU General Public License v3 (GPLv3)
Requires-Python: >=3.11
License-File: LICENSE
Requires-Dist: nemo-toolkit[asr]==2.1.0
Requires-Dist: torch==2.6.0
Requires-Dist: torchaudio==2.6.0
Requires-Dist: transformers==4.48.3
Requires-Dist: omegaconf==2.3.0
Requires-Dist: numpy==1.26.4
